GiantTour.py
SMLGT-0.1.dist-info/METADATA
SMLGT-0.1.dist-info/WHEEL
SMLGT-0.1.dist-info/top_level.txt
SMLGT-0.1.dist-info/RECORD
