Metadata-Version: 2.1
Name: SMLGT
Version: 0.1
Summary: create giant tour
Home-page: UNKNOWN
Author: Mr. Hanh
License: LICENSE.txt
Platform: UNKNOWN
Classifier: Programming Language :: Python :: 2.7
Classifier: License :: OSI Approved :: MIT License
Requires-Dist: ortools
Requires-Dist: kmedoids
